mlx/robot2rst/__init__.py
mlx/robot2rst/__version__.py
mlx/robot2rst/robot2rst.mako
mlx/robot2rst/robot2rst.py
mlx/robot2rst/robot_parser.py
mlx_robot2rst-3.5.2.dist-info/licenses/LICENSE
mlx_robot2rst-3.5.2.dist-info/METADATA
mlx_robot2rst-3.5.2.dist-info/WHEEL
mlx_robot2rst-3.5.2.dist-info/entry_points.txt
mlx_robot2rst-3.5.2.dist-info/top_level.txt
mlx_robot2rst-3.5.2.dist-info/RECORD
